tanglegram/__init__.py
tanglegram/tangle.py
tanglegram-0.2.0.dist-info/LICENSE
tanglegram-0.2.0.dist-info/METADATA
tanglegram-0.2.0.dist-info/WHEEL
tanglegram-0.2.0.dist-info/top_level.txt
tanglegram-0.2.0.dist-info/RECORD
