Metadata-Version: 2.1
Name: tanglegram
Version: 0.2.0
Summary: Plot simple tanglegrams from two dendrograms
Home-page: https://github.com/schlegelp/tanglegram
Author: Philipp Schlegel
Author-email: pms70@cam.ac.uk
License: GNU GPL V3
Keywords: python tanglegram dendrogram
Platform: UNKNOWN
Classifier: Development Status :: 5 - Production/Stable
Classifier: Intended Audience :: Science/Research
Classifier: Topic :: Scientific/Engineering :: Bio-Informatics
Classifier: License :: OSI Approved :: GNU General Public License v3 or later (GPLv3+)
Classifier: Programming Language :: Python :: 3
Classifier: Programming Language :: Python :: 3.6
Classifier: Programming Language :: Python :: 3.7
Classifier: Programming Language :: Python :: 3.8
Classifier: Programming Language :: Python :: 3.9
Classifier: Programming Language :: Python :: 3.10
Requires-Python: >=3
License-File: LICENSE
Requires-Dist: scipy (>=0.18.1)
Requires-Dist: numpy (>=1.12.1)
Requires-Dist: pandas
Requires-Dist: matplotlib (>=2.0.0)
Requires-Dist: tqdm
